bipp_cuda12x.libs/libfftw3f_omp-169829c5.so.3.3.2
bipp_cuda12x.libs/libfftw3-17cc48a2.so.3.3.2
bipp_cuda12x.libs/libfinufft-8147e03f.so
bipp_cuda12x.libs/libquadmath-96973f99.so.0.0.0
bipp_cuda12x.libs/libgomp-a34b3233.so.1.0.0
bipp_cuda12x.libs/libcufinufft-822abecd.so
bipp_cuda12x.libs/libgfortran-91cc3cb1.so.3.0.0
bipp_cuda12x.libs/libfftw3_omp-e6138547.so.3.3.2
bipp_cuda12x.libs/libopenblaso-r0-70c28697.3.3.so
bipp_cuda12x.libs/libfftw3f-4367ce36.so.3.3.2
bipp_cuda12x-0.1.3.dist-info/WHEEL
bipp_cuda12x-0.1.3.dist-info/LICENSE
bipp_cuda12x-0.1.3.dist-info/top_level.txt
bipp_cuda12x-0.1.3.dist-info/RECORD
bipp_cuda12x-0.1.3.dist-info/METADATA
bipp/array.py
bipp/__init__.py
bipp/beamforming.py
bipp/instrument.py
bipp/statistics.py
bipp/pybipp.cpython-312-x86_64-linux-gnu.so
bipp/frame.py
bipp/source.py
bipp/measurement_set.py
bipp/gram.py
bipp/parameter_estimator.py
bipp/core.py
bipp/filter.py
bipp/data/instrument/LOFAR.csv
bipp/data/instrument/MWA.csv
bipp/imot_tools/__init__.py
bipp/imot_tools/data/math/special/ive_threshold.csv
bipp/imot_tools/data/math/special/jv_threshold.csv
bipp/imot_tools/data/math/special/jv_series_threshold.csv
bipp/imot_tools/data/math/special/spherical_jn_series_threshold.csv
bipp/imot_tools/data/math/special/spherical_jn_threshold.csv
bipp/imot_tools/data/io/colormap/algue.csv
bipp/imot_tools/data/io/colormap/lightbulb.csv
bipp/imot_tools/data/io/colormap/lava.csv
bipp/imot_tools/data/io/colormap/jet_alt.csv
bipp/imot_tools/data/io/colormap/fire.csv
bipp/imot_tools/data/io/colormap/aqua.csv
bipp/imot_tools/util/array.py
bipp/imot_tools/util/__init__.py
bipp/imot_tools/util/argcheck.py
bipp/imot_tools/math/__init__.py
bipp/imot_tools/math/linalg.py
bipp/imot_tools/math/func.py
bipp/imot_tools/math/stat.py
bipp/imot_tools/math/special.py
bipp/imot_tools/math/sphere/__init__.py
bipp/imot_tools/math/sphere/grid.py
bipp/imot_tools/math/sphere/transform.py
bipp/imot_tools/math/sphere/interpolate.py
bipp/imot_tools/phased_array/__init__.py
bipp/imot_tools/io/s2image.py
bipp/imot_tools/io/__init__.py
bipp/imot_tools/io/fits.py
bipp/imot_tools/io/plot.py
