Metadata-Version: 2.1
Name: bipp-cuda12x
Version: 0.1.3
Summary: Bluebild imaging algorithm for radio astronomy build with CUDA 12.x
License: GPLv3
Requires-Python: >=3.6
License-File: LICENSE
Requires-Dist: numpy
Requires-Dist: astropy
Requires-Dist: matplotlib
Requires-Dist: tqdm
Requires-Dist: pyproj
Requires-Dist: scipy
Requires-Dist: pandas
Requires-Dist: healpy
Requires-Dist: scikit-learn
Requires-Dist: python-casacore
